ever_loguru/__init__.py
ever_loguru/handler.py
ever_loguru/install.py
ever_loguru/mask.py
ever_loguru/wrapper.py
EverLoguru-1.1.6.dist-info/METADATA
EverLoguru-1.1.6.dist-info/WHEEL
EverLoguru-1.1.6.dist-info/top_level.txt
EverLoguru-1.1.6.dist-info/RECORD
