Metadata-Version: 2.1
Name: EverLoguru
Version: 1.1.6
Summary: Loguru all over the world. | 全世界都在用 Lo~guru~~
Home-page: 
Author: cyan
Author-email: Cyan <lc_shizuku@outlook.com>
Project-URL: Homepage, https://github.com/Chinese-Cyq20100313/loguruEverywhere
Project-URL: Bug Tracker, https://github.com/Chinese-Cyq20100313/loguruEverywhere/issues
Classifier: Programming Language :: Python :: 3
Classifier: Operating System :: OS Independent
Requires: loguru
Requires-Python: >=3.8
